enhancedocs/__init__.py
enhancedocs/commands/__init__.py
enhancedocs/commands/alpha/__init__.py
enhancedocs/commands/alpha/projects/__init__.py
enhancedocs/commands/alpha/projects/create.py
enhancedocs/commands/alpha/sources/__init__.py
enhancedocs/commands/alpha/sources/web.py
enhancedocs/commands/ask.py
enhancedocs/commands/build.py
enhancedocs/commands/push.py
enhancedocs/config.py
enhancedocs/main.py
enhancedocs/utils.py
enhancedocs-0.6.0.dist-info/LICENSE
enhancedocs-0.6.0.dist-info/METADATA
enhancedocs-0.6.0.dist-info/WHEEL
enhancedocs-0.6.0.dist-info/entry_points.txt
enhancedocs-0.6.0.dist-info/RECORD
