Metadata-Version: 2.1
Name: enhancedocs
Version: 0.6.0
Summary: EnhanceDocs Command Line Interface (CLI)
License: Apache-2.0
Author: Alvaro Molina
Author-email: alw3ys@gmail.com
Requires-Python: >=3.11,<4.0
Classifier: License :: OSI Approved :: Apache Software License
Classifier: Programming Language :: Python :: 3
Classifier: Programming Language :: Python :: 3.11
Requires-Dist: click (>=8.1.3,<9.0.0)
Requires-Dist: pathspec (>=0.11.1,<0.12.0)
Requires-Dist: requests (>=2.29.0,<3.0.0)
Requires-Dist: sentry-sdk (>=1.21.0,<2.0.0)
